scopus_citations_tool/__init__.py
scopus_citations_tool/__main__.py
scopus_citations_tool/cli/__init__.py
scopus_citations_tool/cli/cli.py
scopus_citations_tool/cli/common.py
scopus_citations_tool/exporters/__init__.py
scopus_citations_tool/exporters/base.py
scopus_citations_tool/exporters/csv_exporter.py
scopus_citations_tool/logger/__init__.py
scopus_citations_tool/logger/logger.py
scopus_citations_tool/logger/logger_config.py
scopus_citations_tool-1.2.0.dist-info/METADATA
scopus_citations_tool-1.2.0.dist-info/WHEEL
scopus_citations_tool-1.2.0.dist-info/entry_points.txt
scopus_citations_tool-1.2.0.dist-info/RECORD
