Metadata-Version: 2.4
Name: scopus-citations-tool
Version: 1.2.0
Author-email: Anatoliy Lazovyi <Lazoviy3000@ya.ru>
Requires-Python: ~=3.13
Requires-Dist: loguru<0.8,>=0.7.2
Requires-Dist: orcid-scraping<0.2,>=0.1.0
Requires-Dist: pydantic<3,>=2.6.4
Requires-Dist: scopus-scraping<0.2,>=0.1.0
Requires-Dist: selenium<5,>=4.18.1
Requires-Dist: tqdm<5,>=4.66.2
